git_lazy-0.2.1.dist-info/DESCRIPTION.rst
git_lazy-0.2.1.dist-info/METADATA
git_lazy-0.2.1.dist-info/RECORD
git_lazy-0.2.1.dist-info/WHEEL
git_lazy-0.2.1.dist-info/entry_points.txt
git_lazy-0.2.1.dist-info/metadata.json
git_lazy-0.2.1.dist-info/top_level.txt
gitlazy/__init__.py
gitlazy/gitlazy.py
