Metadata-Version: 2.0
Name: git-lazy
Version: 0.2.1
Summary: Sync repos across development environments. Bulk status|push|pull operations on git repos.
Home-page: https://bitbucket.org/tsantor/git-lazy
Author: Tim Santor
Author-email: tsantor@xstudios.agency
License: MIT
Keywords: git-lazy
Platform: UNKNOWN
Classifier: Development Status :: 2 - Pre-Alpha
Classifier: Intended Audience :: Developers
Classifier: License :: OSI Approved :: BSD License
Classifier: Natural Language :: English
Classifier: Programming Language :: Python :: 2
Classifier: Programming Language :: Python :: 2.6
Classifier: Programming Language :: Python :: 2.7
Classifier: Programming Language :: Python :: 3
Classifier: Programming Language :: Python :: 3.3
Classifier: Programming Language :: Python :: 3.4
Requires-Dist: python-bash-utils
Requires-Dist: six
